{
  "project_info": {
    "project_number": "456825306628",
    "project_id": "mobile-4c03a",
    "storage_bucket": "mobile-4c03a.appspot.com"
  },
  "client": [
    {
      "client_info": {
        "mobilesdk_app_id": "1:456825306628:android:b254592e4d1af329dabf51",
        "android_client_info": {
          "package_name": "com.example.signin_signup_auth_firebase"
        }
      },
      "oauth_client": [
        {
          "client_id": "456825306628-vpimihl6tl6bpsp926rqthq7nbim132p.apps.googleusercontent.com",
          "client_type": 3
        }
      ],
      "api_key": [
        {
          "current_key": "AIzaSyAx11BU2FMNc9ZvxIJbc1ZYXJ9Jkj1TCJw"
        }
      ],
      "services": {
        "appinvite_service": {
          "other_platform_oauth_client": [
            {
              "client_id": "456825306628-vpimihl6tl6bpsp926rqthq7nbim132p.apps.googleusercontent.com",
              "client_type": 3
            }
          ]
        }
      }
    }
  ],
  "configuration_version": "1"
}